quicdraw/__init__.py
quicdraw/quicdraw.py
quicdraw-0.8.29.dist-info/licenses/LICENSE
quicdraw-0.8.29.dist-info/METADATA
quicdraw-0.8.29.dist-info/WHEEL
quicdraw-0.8.29.dist-info/entry_points.txt
quicdraw-0.8.29.dist-info/top_level.txt
quicdraw-0.8.29.dist-info/RECORD
