Metadata-Version: 2.4
Name: quicdraw
Version: 0.8.29
Summary: QuicDraw(H3) Fuzzing and Racing HTTP/3 (over QUIC)
Author-email: Maor A <m2a2@users.noreply.github.com>
License-Expression: Apache-2.0
Project-URL: Homepage, https://github.com/cyberark/QuicDrawh3
Project-URL: Issues, https://github.com/cyberark/QuicDrawh3/issues
Keywords: HTTP/3,QUIC,Web,Security,Fuzzing,Fuzz,Race-Conditions,Web Security,Web Application Security,HTTP3
Classifier: Programming Language :: Python :: 3
Classifier: Operating System :: OS Independent
Classifier: Framework :: AsyncIO
Classifier: Topic :: Security
Classifier: Topic :: Internet :: WWW/HTTP
Classifier: Topic :: System :: Networking
Requires-Python: >=3.9
License-File: LICENSE
Requires-Dist: aioquic
Requires-Dist: wsproto
Dynamic: license-file
